crazy_piano/__init__.py
crazy_piano/frequencies.py
crazy_piano-0.0.1.dist-info/LICENSE
crazy_piano-0.0.1.dist-info/METADATA
crazy_piano-0.0.1.dist-info/WHEEL
crazy_piano-0.0.1.dist-info/top_level.txt
crazy_piano-0.0.1.dist-info/RECORD
