Metadata-Version: 2.1
Name: crazy-piano
Version: 0.0.1
Summary: A package for exploring the fundamentals of how we define music.
Home-page: https://github.com/mike-altonji/crazy-piano
Author: Michael Altonji
Author-email: mikealtonji@gmail.com
License: UNKNOWN
Platform: UNKNOWN
Classifier: Programming Language :: Python :: 3
Classifier: License :: OSI Approved :: MIT License
Classifier: Operating System :: OS Independent
Requires-Dist: pandas
